{
      "word_count": 5348,
      "processed_language": "en",
      "personality": [
            {
                  "trait_id": "big5_openness",
                  "name": "Openness",
                  "category": "personality",
                  "percentile": 0.9592574192599506,
                  "raw_score": 0.8042725026974787,
                  "significant": true,
                  "children": [
                        {
                              "trait_id": "facet_adventurousness",
                              "name": "Adventurousness",
                              "category": "personality",
                              "percentile": 0.7756540821359228,
                              "raw_score": 0.5317624375972224,
                              "significant": true
                        },
                        {
                              "trait_id": "facet_artistic_interests",
                              "name": "Artistic interests",
                              "category": "personality",
                              "percentile": 0.9463420234340005,
                              "raw_score": 0.7468473746114612,
                              "significant": true
                        },
                        {
                              "trait_id": "facet_emotionality",
                              "name": "Emotionality",
                              "category": "personality",
                              "percentile": 0.7687585095760137,
                              "raw_score": 0.6781505250131297,
                              "significant": true
                        },
                        {
                              "trait_id": "facet_imagination",
                              "name": "Imagination",
                              "category": "personality",
                              "percentile": 0.8248080619291698,
                              "raw_score": 0.7812431549787604,
                              "significant": true
                        },
                        {
                              "trait_id": "facet_intellect",
                              "name": "Intellect",
                              "category": "personality",
                              "percentile": 0.9941580170360769,
                              "raw_score": 0.7239617494016213,
                              "significant": true
                        },
                        {
                              "trait_id": "facet_liberalism",
                              "name": "Authority-challenging",
                              "category": "personality",
                              "percentile": 0.9072581842377401,
                              "raw_score": 0.5829174949639332,
                              "significant": true
                        }
                  ]
            },
            {
                  "trait_id": "big5_conscientiousness",
                  "name": "Conscientiousness",
                  "category": "personality",
                  "percentile": 0.6952826888678851,
                  "raw_score": 0.65187891381755,
                  "significant": true,
                  "children": [
                        {
                              "trait_id": "facet_achievement_striving",
                              "name": "Achievement striving",
                              "category": "personality",
                              "percentile": 0.8006739985942618,
                              "raw_score": 0.7330852282749731,
                              "significant": true
                        },
                        {
                              "trait_id": "facet_cautiousness",
                              "name": "Cautiousness",
                              "category": "personality",
                              "percentile": 0.8060677476395812,
                              "raw_score": 0.5469822426706936,
                              "significant": true
                        },
                        {
                              "trait_id": "facet_dutifulness",
                              "name": "Dutifulness",
                              "category": "personality",
                              "percentile": 0.6630556275117747,
                              "raw_score": 0.6692060413495351,
                              "significant": true
                        },
                        {
                              "trait_id": "facet_orderliness",
                              "name": "Orderliness",
                              "category": "personality",
                              "percentile": 0.5060804953031172,
                              "raw_score": 0.494655253243753,
                              "significant": true
                        },
                        {
                              "trait_id": "facet_self_discipline",
                              "name": "Self-discipline",
                              "category": "personality",
                              "percentile": 0.5242277886409291,
                              "raw_score": 0.5735482077656092,
                              "significant": true
                        },
                        {
                              "trait_id": "facet_self_efficacy",
                              "name": "Self-efficacy",
                              "category": "personality",
                              "percentile": 0.7193261430467466,
                              "raw_score": 0.7735268511597984,
                              "significant": true
                        }
                  ]
            },
            {
                  "trait_id": "big5_extraversion",
                  "name": "Extraversion",
                  "category": "personality",
                  "percentile": 0.3045981513202028,
                  "raw_score": 0.5281936342600148,
                  "significant": true,
                  "children": [
                        {
                              "trait_id": "facet_activity_level",
                              "name": "Activity level",
                              "category": "personality",
                              "percentile": 0.8637990493294158,
                              "raw_score": 0.5965395661822727,
                              "significant": true
                        },
                        {
                              "trait_id": "facet_assertiveness",
                              "name": "Assertiveness",
                              "category": "personality",
                              "percentile": 0.8107876678886439,
                              "raw_score": 0.6880903187527807,
                              "significant": true
                        },
                        {
                              "trait_id": "facet_cheerfulness",
                              "name": "Cheerfulness",
                              "category": "personality",
                              "percentile": 0.18378835958523126,
                              "raw_score": 0.5879008089235989,
                              "significant": true
                        },
                        {
                              "trait_id": "facet_excitement_seeking",
                              "name": "Excitement-seeking",
                              "category": "personality",
                              "percentile": 0.3154124013644949,
                              "raw_score": 0.5832282667430415,
                              "significant": true
                        },
                        {
                              "trait_id": "facet_friendliness",
                              "name": "Outgoing",
                              "category": "personality",
                              "percentile": 0.42581255025530657,
                              "raw_score": 0.5511072780683907,
                              "significant": true
                        },
                        {
                              "trait_id": "facet_gregariousness",
                              "name": "Gregariousness",
                              "category": "personality",
                              "percentile": 0.057328548188286366,
                              "raw_score": 0.372238119633052,
                              "significant": true
                        }
                  ]
            },
            {
                  "trait_id": "big5_agreeableness",
                  "name": "Agreeableness",
                  "category": "personality",
                  "percentile": 0.2739184693921154,
                  "raw_score": 0.718305761564775,
                  "significant": true,
                  "children": [
                        {
                              "trait_id": "facet_altruism",
                              "name": "Altruism",
                              "category": "personality",
                              "percentile": 0.959317740251392,
                              "raw_score": 0.7662290735894427,
                              "significant": true
                        },
                        {
                              "trait_id": "facet_cooperation",
                              "name": "Cooperation",
                              "category": "personality",
                              "percentile": 0.737721629963138,
                              "raw_score": 0.6177269078028982,
                              "significant": true
                        },
                        {
                              "trait_id": "facet_modesty",
                              "name": "Modesty",
                              "category": "personality",
                              "percentile": 0.5827665889895683,
                              "raw_score": 0.4594026847526158,
                              "significant": true
                        },
                        {
                              "trait_id": "facet_morality",
                              "name": "Uncompromising",
                              "category": "personality",
                              "percentile": 0.8046387542041944,
                              "raw_score": 0.6663093780341167,
                              "significant": true
                        },
                        {
                              "trait_id": "facet_sympathy",
                              "name": "Sympathy",
                              "category": "personality",
                              "percentile": 0.9976512706936205,
                              "raw_score": 0.7714286057216448,
                              "significant": true
                        },
                        {
                              "trait_id": "facet_trust",
                              "name": "Trust",
                              "category": "personality",
                              "percentile": 0.7656086212111864,
                              "raw_score": 0.6156475684586143,
                              "significant": true
                        }
                  ]
            },
            {
                  "trait_id": "big5_neuroticism",
                  "name": "Emotional range",
                  "category": "personality",
                  "percentile": 0.47195957215352996,
                  "raw_score": 0.5366510198958435,
                  "significant": true,
                  "children": [
                        {
                              "trait_id": "facet_anger",
                              "name": "Fiery",
                              "category": "personality",
                              "percentile": 0.15253380455460264,
                              "raw_score": 0.47962841559972813,
                              "significant": true
                        },
                        {
                              "trait_id": "facet_anxiety",
                              "name": "Prone to worry",
                              "category": "personality",
                              "percentile": 0.25708238885025386,
                              "raw_score": 0.5496223975405025,
                              "significant": true
                        },
                        {
                              "trait_id": "facet_depression",
                              "name": "Melancholy",
                              "category": "personality",
                              "percentile": 0.5082111428333567,
                              "raw_score": 0.44974260625947315,
                              "significant": true
                        },
                        {
                              "trait_id": "facet_immoderation",
                              "name": "Immoderation",
                              "category": "personality",
                              "percentile": 0.09460075555970893,
                              "raw_score": 0.45012987670370896,
                              "significant": true
                        },
                        {
                              "trait_id": "facet_self_consciousness",
                              "name": "Self-consciousness",
                              "category": "personality",
                              "percentile": 0.4192697991357418,
                              "raw_score": 0.5359927221389614,
                              "significant": true
                        },
                        {
                              "trait_id": "facet_vulnerability",
                              "name": "Susceptible to stress",
                              "category": "personality",
                              "percentile": 0.24225339317888572,
                              "raw_score": 0.42308304133863667,
                              "significant": true
                        }
                  ]
            }
      ],
      "needs": [
            {
                  "trait_id": "need_challenge",
                  "name": "Challenge",
                  "category": "needs",
                  "percentile": 0.038269969125365344,
                  "raw_score": 0.6523520197628232,
                  "significant": true
            },
            {
                  "trait_id": "need_closeness",
                  "name": "Closeness",
                  "category": "needs",
                  "percentile": 0.2637476675456112,
                  "raw_score": 0.765316082373936,
                  "significant": true
            },
            {
                  "trait_id": "need_curiosity",
                  "name": "Curiosity",
                  "category": "needs",
                  "percentile": 0.7214807256549745,
                  "raw_score": 0.8321059739593002,
                  "significant": true
            },
            {
                  "trait_id": "need_excitement",
                  "name": "Excitement",
                  "category": "needs",
                  "percentile": 0.08406145584339725,
                  "raw_score": 0.5757222044561193,
                  "significant": true
            },
            {
                  "trait_id": "need_harmony",
                  "name": "Harmony",
                  "category": "needs",
                  "percentile": 0.29352386027299604,
                  "raw_score": 0.7905036886659662,
                  "significant": true
            },
            {
                  "trait_id": "need_ideal",
                  "name": "Ideal",
                  "category": "needs",
                  "percentile": 0.0663128348365622,
                  "raw_score": 0.6195895879580342,
                  "significant": true
            },
            {
                  "trait_id": "need_liberty",
                  "name": "Liberty",
                  "category": "needs",
                  "percentile": 0.1292694815907212,
                  "raw_score": 0.6941852127471102,
                  "significant": true
            },
            {
                  "trait_id": "need_love",
                  "name": "Love",
                  "category": "needs",
                  "percentile": 0.0957514274953537,
                  "raw_score": 0.7051214421554385,
                  "significant": true
            },
            {
                  "trait_id": "need_practicality",
                  "name": "Practicality",
                  "category": "needs",
                  "percentile": 0.0990400888568349,
                  "raw_score": 0.6999660748646575,
                  "significant": true
            },
            {
                  "trait_id": "need_self_expression",
                  "name": "Self-expression",
                  "category": "needs",
                  "percentile": 0.24495993740166638,
                  "raw_score": 0.6512219613308375,
                  "significant": true
            },
            {
                  "trait_id": "need_stability",
                  "name": "Stability",
                  "category": "needs",
                  "percentile": 0.3259412839607833,
                  "raw_score": 0.7200813014706496,
                  "significant": true
            },
            {
                  "trait_id": "need_structure",
                  "name": "Structure",
                  "category": "needs",
                  "percentile": 0.48699153856615734,
                  "raw_score": 0.6951948415349913,
                  "significant": true
            }
      ],
      "values": [
            {
                  "trait_id": "value_conservation",
                  "name": "Conservation",
                  "category": "values",
                  "percentile": 0.11091872159739541,
                  "raw_score": 0.610413987404657,
                  "significant": true
            },
            {
                  "trait_id": "value_openness_to_change",
                  "name": "Openness to change",
                  "category": "values",
                  "percentile": 0.5512268185809646,
                  "raw_score": 0.78923336635751,
                  "significant": true
            },
            {
                  "trait_id": "value_hedonism",
                  "name": "Hedonism",
                  "category": "values",
                  "percentile": 0.04152916086399999,
                  "raw_score": 0.6274401643514228,
                  "significant": true
            },
            {
                  "trait_id": "value_self_enhancement",
                  "name": "Self-enhancement",
                  "category": "values",
                  "percentile": 0.01777554328985481,
                  "raw_score": 0.6141100788983855,
                  "significant": true
            },
            {
                  "trait_id": "value_self_transcendence",
                  "name": "Self-transcendence",
                  "category": "values",
                  "percentile": 0.3094242870845252,
                  "raw_score": 0.8248559072593887,
                  "significant": true
            }
      ],
      "warnings": [],
      "Actor Name": "Randeep Hooda",
      "Image Link": "https://pbs.twimg.com/profile_images/1253611619084414976/U3V_DZ6d_400x400.jpg"
}
